semiconductor_sim/__init__.py
semiconductor_sim/cli.py
semiconductor_sim/py.typed
semiconductor_sim/devices/__init__.py
semiconductor_sim/devices/base.py
semiconductor_sim/devices/bjt.py
semiconductor_sim/devices/led.py
semiconductor_sim/devices/mos_capacitor.py
semiconductor_sim/devices/photodiode.py
semiconductor_sim/devices/pin_diode.py
semiconductor_sim/devices/pn_junction.py
semiconductor_sim/devices/schottky.py
semiconductor_sim/devices/solar_cell.py
semiconductor_sim/devices/tunnel_diode.py
semiconductor_sim/devices/varactor_diode.py
semiconductor_sim/devices/zener_diode.py
semiconductor_sim/materials/__init__.py
semiconductor_sim/materials/registry.py
semiconductor_sim/models/__init__.py
semiconductor_sim/models/auger_recombination.py
semiconductor_sim/models/bandgap.py
semiconductor_sim/models/high_frequency.py
semiconductor_sim/models/mobility.py
semiconductor_sim/models/radiative_recombination.py
semiconductor_sim/models/recombination.py
semiconductor_sim/models/srh.py
semiconductor_sim/utils/__init__.py
semiconductor_sim/utils/constants.py
semiconductor_sim/utils/numerics.py
semiconductor_sim/utils/plotting.py
semiconductor_sim-1.0.5.dist-info/licenses/LICENSE
semiconductor_sim-1.0.5.dist-info/METADATA
semiconductor_sim-1.0.5.dist-info/WHEEL
semiconductor_sim-1.0.5.dist-info/entry_points.txt
semiconductor_sim-1.0.5.dist-info/top_level.txt
semiconductor_sim-1.0.5.dist-info/RECORD
