Metadata-Version: 2.4
Name: semiconductor-sim
Version: 1.0.5
Summary: A simulation library for basic semiconductor devices aimed at undergraduates.
Author-email: Michael Kennedy <michael.patrick.kennedy@outlook.ie>
License: MIT License
Project-URL: Homepage, https://github.com/kennedym-ds/semiconductor_sim
Project-URL: Repository, https://github.com/kennedym-ds/semiconductor_sim
Project-URL: Documentation, https://kennedym-ds.github.io/semiconductor_sim/
Project-URL: Bug-Tracker, https://github.com/kennedym-ds/semiconductor_sim/issues
Project-URL: Changelog, https://github.com/kennedym-ds/semiconductor_sim/blob/main/CHANGELOG.md
Keywords: semiconductor,devices,pn-junction,led,solar-cell,zener,mos,education,simulation
Classifier: Development Status :: 5 - Production/Stable
Classifier: Intended Audience :: Education
Classifier: Intended Audience :: Science/Research
Classifier: Topic :: Scientific/Engineering
Classifier: Topic :: Education
Classifier: Programming Language :: Python
Classifier: Programming Language :: Python :: 3
Classifier: Programming Language :: Python :: 3.10
Classifier: Programming Language :: Python :: 3.11
Classifier: Programming Language :: Python :: 3.12
Classifier: Programming Language :: Python :: 3.13
Classifier: Operating System :: OS Independent
Requires-Python: >=3.10
License-File: LICENSE
Requires-Dist: numpy
Requires-Dist: matplotlib
Requires-Dist: scipy
Requires-Dist: plotly
Requires-Dist: ipywidgets
Requires-Dist: joblib
Provides-Extra: dev
Requires-Dist: pre-commit; extra == "dev"
Requires-Dist: ruff; extra == "dev"
Requires-Dist: mypy; extra == "dev"
Requires-Dist: pytest; extra == "dev"
Requires-Dist: coverage; extra == "dev"
Requires-Dist: hypothesis; extra == "dev"
Requires-Dist: pip-audit; extra == "dev"
Requires-Dist: mkdocs-material; extra == "dev"
Requires-Dist: mkdocstrings; extra == "dev"
Requires-Dist: mkdocstrings-python; extra == "dev"
Requires-Dist: build; extra == "dev"
Dynamic: license-file
